osclient/__init__.py
osclient/openstack.py
osclient/openstack2.py
osclient-0.1.1.dist-info/METADATA
osclient-0.1.1.dist-info/WHEEL
osclient-0.1.1.dist-info/top_level.txt
osclient-0.1.1.dist-info/RECORD
