Metadata-Version: 2.4
Name: osclient
Version: 0.1.1
Summary: OpenStack client library with simplified authentication
Home-page: https://github.com/ntoand/osclient
Author: Toan Nguyen
Author-email: Toan Nguyen <ntoand@gmail.com>
License: MIT
Keywords: openstack,cloud,client
Classifier: Development Status :: 3 - Alpha
Classifier: Intended Audience :: Developers
Classifier: License :: OSI Approved :: MIT License
Classifier: Programming Language :: Python :: 3
Classifier: Programming Language :: Python :: 3.6
Classifier: Programming Language :: Python :: 3.7
Classifier: Programming Language :: Python :: 3.8
Classifier: Programming Language :: Python :: 3.9
Classifier: Programming Language :: Python :: 3.10
Classifier: Programming Language :: Python :: 3.11
Classifier: Topic :: Software Development :: Libraries :: Python Modules
Requires-Python: >=3.6
Requires-Dist: keystoneauth1>=4.0.0
Requires-Dist: python-novaclient>=17.0.0
Requires-Dist: python-keystoneclient>=4.0.0
Requires-Dist: python-cinderclient>=7.0.0
Requires-Dist: python-neutronclient>=7.0.0
Requires-Dist: nectarallocationclient>=1.0.0
Requires-Dist: python-glanceclient>=3.0.0
Requires-Dist: requests>=2.25.0
Provides-Extra: dev
Requires-Dist: pytest>=6.0; extra == "dev"
Requires-Dist: pytest-cov>=2.0; extra == "dev"
Requires-Dist: black>=21.0; extra == "dev"
Requires-Dist: flake8>=3.8; extra == "dev"
Dynamic: author
Dynamic: home-page
Dynamic: requires-python
